nalenc/__init__.py
nalenc/nalenc.py
nalenc-1.2.0.dist-info/COPYING
nalenc-1.2.0.dist-info/COPYING.LESSER
nalenc-1.2.0.dist-info/LICENSE
nalenc-1.2.0.dist-info/METADATA
nalenc-1.2.0.dist-info/WHEEL
nalenc-1.2.0.dist-info/top_level.txt
nalenc-1.2.0.dist-info/RECORD
