Metadata-Version: 2.1
Name: nalenc
Version: 1.2.0
Summary: Lightweight symetric encryption
Author-email: David Lishchyshen <microdaika1@gmail.com>
Project-URL: Homepage, https://github.com/AsfhtgkDavid/NAL-Encryption
Keywords: encryption,lightweight,symetric,secure
Classifier: License :: OSI Approved :: GNU Lesser General Public License v3 (LGPLv3)
Classifier: License :: OSI Approved :: GNU Lesser General Public License v3 or later (LGPLv3+)
Classifier: Programming Language :: Python :: 3
Classifier: Topic :: Security
Classifier: Topic :: Security :: Cryptography
Classifier: Topic :: Software Development :: Libraries
Classifier: Topic :: Software Development :: Libraries :: Python Modules
Classifier: Typing :: Typed
Requires-Python: >=3.10
License-File: LICENSE
License-File: COPYING
License-File: COPYING.LESSER
Requires-Dist: numpy>=2.1.0
